{"cameraMode":{"drawMode":0,"name":"Shaded","section":"Shading Mode"},"sceneLighting":true,"audioPlay":false,"sceneViewState":{"showFog":true,"showMaterialUpdate":false,"showSkybox":true,"showFlares":true,"showImageEffects":true,"showParticleSystems":true,"showVisualEffectGraphs":true,"m_FxEnabled":true},"in2DMode":false,"pivot":{"x":2.181190252304077,"y":-4.075489521026611,"z":10.657926559448243},"rotation":{"x":-0.14366745948791505,"y":0.0770493820309639,"z":-0.011218860745429993,"w":-0.9866527318954468},"size":9.899160385131836,"orthographic":false}