{"cameraMode":{"drawMode":0,"name":"Shaded","section":"Shading Mode"},"sceneLighting":true,"audioPlay":false,"sceneViewState":{"showFog":true,"showMaterialUpdate":false,"showSkybox":true,"showFlares":true,"showImageEffects":true,"showParticleSystems":true,"showVisualEffectGraphs":true,"m_FxEnabled":true},"in2DMode":false,"pivot":{"x":4.5855512619018559,"y":0.5580015182495117,"z":2.5850820541381838},"rotation":{"x":-0.13345953822135926,"y":-0.6223308444023132,"z":0.10890708863735199,"w":-0.7637580037117004},"size":0.55901700258255,"orthographic":false}